{"frames": [

{
	"filename": "wordmaster-hand_0",
	"frame": {"x":2918,"y":0,"w":844,"h":2369},
	"rotated": false,
	"trimmed": true,
	"spriteSourceSize": {"x":24,"y":33,"w":844,"h":2369},
	"sourceSize": {"w":900,"h":2430}
},
{
	"filename": "wordmaster-hand_1",
	"frame": {"x":2071,"y":0,"w":845,"h":2371},
	"rotated": false,
	"trimmed": true,
	"spriteSourceSize": {"x":31,"y":33,"w":845,"h":2371},
	"sourceSize": {"w":900,"h":2430}
},
{
	"filename": "wordmaster-paper_big",
	"frame": {"x":0,"y":0,"w":2069,"h":3037},
	"rotated": false,
	"trimmed": true,
	"spriteSourceSize": {"x":46,"y":11,"w":2069,"h":3037},
	"sourceSize": {"w":2160,"h":3075}
}],
"meta": {
	"app": "http://www.codeandweb.com/texturepacker",
	"version": "1.0",
	"image": "atlas_3_3.png",
	"format": "RGBA8888",
	"size": {"w":3762,"h":3037},
	"scale": "0.75",
	"smartupdate": "$TexturePacker:SmartUpdate:2c2379de0d74a8e2ca69eea3bafb21b9:46aca08964f09beacbaca59c9945ad31:eddc82f9f74ced3469ba9be1e67c5123$"
}
}
