{"frames": [

{
	"filename": "wordmaster-hand_0",
	"frame": {"x":706,"y":2533,"w":704,"h":1975},
	"rotated": false,
	"trimmed": true,
	"spriteSourceSize": {"x":20,"y":27,"w":704,"h":1975},
	"sourceSize": {"w":750,"h":2025}
},
{
	"filename": "wordmaster-hand_1",
	"frame": {"x":0,"y":2533,"w":704,"h":1976},
	"rotated": false,
	"trimmed": true,
	"spriteSourceSize": {"x":26,"y":27,"w":704,"h":1976},
	"sourceSize": {"w":750,"h":2025}
},
{
	"filename": "wordmaster-paper_big",
	"frame": {"x":0,"y":0,"w":1725,"h":2531},
	"rotated": false,
	"trimmed": true,
	"spriteSourceSize": {"x":38,"y":9,"w":1725,"h":2531},
	"sourceSize": {"w":1800,"h":2563}
}],
"meta": {
	"app": "http://www.codeandweb.com/texturepacker",
	"version": "1.0",
	"image": "atlas_2.5_3.png",
	"format": "RGBA8888",
	"size": {"w":1725,"h":4509},
	"scale": "0.625",
	"smartupdate": "$TexturePacker:SmartUpdate:2c2379de0d74a8e2ca69eea3bafb21b9:46aca08964f09beacbaca59c9945ad31:eddc82f9f74ced3469ba9be1e67c5123$"
}
}
